opt_einsum_fx/__init__.py
opt_einsum_fx/_efficient_shape_prop.py
opt_einsum_fx/_fuse.py
opt_einsum_fx/_opt_ein.py
opt_einsum_fx/_script.py
opt_einsum_fx/fx_utils.py
opt_einsum_fx-0.1.4.dist-info/LICENSE
opt_einsum_fx-0.1.4.dist-info/METADATA
opt_einsum_fx-0.1.4.dist-info/WHEEL
opt_einsum_fx-0.1.4.dist-info/top_level.txt
opt_einsum_fx-0.1.4.dist-info/RECORD
