Metadata-Version: 2.1
Name: opt_einsum_fx
Version: 0.1.4
Summary: Einsum optimization using opt_einsum and PyTorch FX
Home-page: https://github.com/Linux-cpp-lisp/opt_einsum_fx
Author: Linux-cpp-lisp
License: MIT
Project-URL: Bug Tracker, https://github.com/Linux-cpp-lisp/opt_einsum_fx/issues
Platform: UNKNOWN
Classifier: Programming Language :: Python :: 3
Classifier: License :: OSI Approved :: MIT License
Classifier: Operating System :: OS Independent
Classifier: Development Status :: 4 - Beta
Requires-Python: >=3.6
